{"PID": "2825f84e-35c5-11e9-839c-0202761b0892", "p_title": "\u4f1e", "p_content": "//\u597d\u60f3\u8981\u4e0b\u96e8...  \n\u56fe\u6e90\uff1a\u9177\u5b89", "width": 1672, "height": 2508, "username": "Createlite", "p_link": "https://ooo.0o0.ooo/2019/02/21/5c6e80020aa7d.jpg", "local_url": "https://img.dpic.dev/72dd24518ea1c3f2af6f01090c5f4ce1", "TID": "5398f27b-a9f7-11e8-a8ea-0202761b0892", "p_date": "2019-02-22", "theme_color": "#1c271f", "text_color": "#ffffff", "nativePath": "/201902/72dd24518ea1c3f2af6f01090c5f4ce1.jpg", "s1_url": "https://s1.images.dailypics.cn/201902/72dd24518ea1c3f2af6f01090c5f4ce1.jpg", "s2_url": "https://s2.images.dailypics.cn/201902/72dd24518ea1c3f2af6f01090c5f4ce1.jpg", "type": ".jpg", "aspect_ratio": "2:3", "info": {"image": {"size": 0, "format": "null"}, "exif": {}}, "size_b": 0, "size_kb": 0.0, "size_mb": 0.0, "size": "0.0KB", "p_content_html": "<p>//\u597d\u60f3\u8981\u4e0b\u96e8...  <br />\n\u56fe\u6e90\uff1a\u9177\u5b89</p>", "if_today": false, "ago": 1132, "ago_zh": "1132\u5929\u524d"}