{"PID": "35db14ee-aef3-11ea-afa7-c07c56ee9ffc", "p_title": "\u795e\u793e", "p_content": "\u636e\u8bf4\u8fd9\u662f\u5728\u68ee\u6797\u6df1\u5904\u53ea\u6709\u8ff7\u8def\u7684\u4eba\u624d\u80fd\u5230\u8fbe\u7684\u5730\u65b9\u3002  \n\u56fe\u6e90\uff1a[Pixiv@\u4e09\u6e4a\u304b\u304a\u308a](https://www.pixiv.net/artworks/80169412 \"Pixiv@\u4e09\u6e4a\u304b\u304a\u308a\")", "width": 2500, "height": 1765, "username": "Chimon89", "p_link": "https://img.dpic.dev/c1d6352c20381ecb192f61a2a677653e", "local_url": "https://img.dpic.dev/c1d6352c20381ecb192f61a2a677653e", "TID": "e5771003-b4ed-11e8-a8ea-0202761b0892", "p_date": "2020-06-16", "theme_color": "#384d36", "text_color": "#ffffff", "nativePath": "/202006/c1d6352c20381ecb192f61a2a677653e.jpg", "s1_url": "https://s1.images.dailypics.cn/202006/c1d6352c20381ecb192f61a2a677653e.jpg", "s2_url": "https://s2.images.dailypics.cn/202006/c1d6352c20381ecb192f61a2a677653e.jpg", "type": ".jpg", "aspect_ratio": "16:11.3", "info": {"image": {"size": 0, "format": "null"}, "exif": {}}, "size_b": 0, "size_kb": 0.0, "size_mb": 0.0, "size": "0.0KB", "p_content_html": "<p>\u636e\u8bf4\u8fd9\u662f\u5728\u68ee\u6797\u6df1\u5904\u53ea\u6709\u8ff7\u8def\u7684\u4eba\u624d\u80fd\u5230\u8fbe\u7684\u5730\u65b9\u3002  <br />\n\u56fe\u6e90\uff1a<a href=\"https://www.pixiv.net/artworks/80169412\" title=\"Pixiv@\u4e09\u6e4a\u304b\u304a\u308a\">Pixiv@\u4e09\u6e4a\u304b\u304a\u308a</a></p>", "if_today": false, "ago": 650, "ago_zh": "650\u5929\u524d"}