{"PID": "7e4f183f-5e00-11ea-8f08-0202761b0196", "p_title": "\u590f\u65e5\u665a\u971e", "p_content": "\u8fd9\u5f20\u7167\u7247\u62cd\u6444\u4e8e 19 \u5e74 8 \u6708\uff0c\u611f\u89c9\u590f\u5929\u7684\u665a\u971e\u603b\u6bd4\u51ac\u5929\u597d\u770b\uff01  \n//\u597d\u50cf\u590f\u5929\u65e9\u70b9\u5230\u6765\uff0c\u5927\u5bb6\u90fd\u53ef\u4ee5\u5feb\u5feb\u4e50\u4e50\u7684\u51fa\u53bb\u73a9\u5566  \n> \u56fe\u6e90\uff1aDaliypics@\u6a58\u5b50\u5440  \n> \u62cd\u6444\u5668\u6750\uff1aApple iPhone 7 Plus f/1.8 with Photoshop  \n> \u62cd\u6444\u5730\uff1a\u8302\u540d\uff0c\u5e7f\u4e1c", "width": 1200, "height": 2135, "username": "\u6a58\u5b50\u5440", "p_link": "https://img.dpic.dev/8978a3b7436cc14fa6d086da022b05c0", "local_url": "https://img.dpic.dev/8978a3b7436cc14fa6d086da022b05c0", "TID": "5398f27b-a9f7-11e8-a8ea-0202761b0892", "p_date": "2020-03-06", "theme_color": "#7b95ba", "text_color": "#000000", "nativePath": "/202003/8978a3b7436cc14fa6d086da022b05c0.jpg", "s1_url": "https://s1.images.dailypics.cn/202003/8978a3b7436cc14fa6d086da022b05c0.jpg", "s2_url": "https://s2.images.dailypics.cn/202003/8978a3b7436cc14fa6d086da022b05c0.jpg", "type": ".jpg", "aspect_ratio": "9:16", "info": {"image": {"size": 0, "format": "null"}, "exif": {}}, "size_b": 0, "size_kb": 0.0, "size_mb": 0.0, "size": "0.0KB", "p_content_html": "<p>\u8fd9\u5f20\u7167\u7247\u62cd\u6444\u4e8e 19 \u5e74 8 \u6708\uff0c\u611f\u89c9\u590f\u5929\u7684\u665a\u971e\u603b\u6bd4\u51ac\u5929\u597d\u770b\uff01  <br />\n//\u597d\u50cf\u590f\u5929\u65e9\u70b9\u5230\u6765\uff0c\u5927\u5bb6\u90fd\u53ef\u4ee5\u5feb\u5feb\u4e50\u4e50\u7684\u51fa\u53bb\u73a9\u5566    </p>\n<blockquote>\n<p>\u56fe\u6e90\uff1aDaliypics@\u6a58\u5b50\u5440  <br />\n\u62cd\u6444\u5668\u6750\uff1aApple iPhone 7 Plus f/1.8 with Photoshop  <br />\n\u62cd\u6444\u5730\uff1a\u8302\u540d\uff0c\u5e7f\u4e1c</p>\n</blockquote>", "if_today": false, "ago": 569, "ago_zh": "569\u5929\u524d"}