{"PID": "a774155c-6515-11e9-a958-f23c914b97eb", "p_title": "\u65e0\u9898", "p_content": "//\u6211\u4e0e\u4f60\u7684\u5e78\u798f\u3002", "width": 5322, "height": 3553, "username": "\u7a7a\u767d", "p_link": "https://ws3.sinaimg.cn/large/005SeDP8gy1g2ataxzeqcj343u2qpnpd.jpg", "local_url": "https://img.dpic.dev/e54d9316713fc1ea600f34e86a1fbe5e", "TID": "e5771003-b4ed-11e8-a8ea-0202761b0892", "p_date": "2019-04-25", "theme_color": "#162b3a", "text_color": "#ffffff", "nativePath": "/201904/e54d9316713fc1ea600f34e86a1fbe5e.jpg", "s1_url": "https://s1.images.dailypics.cn/201904/e54d9316713fc1ea600f34e86a1fbe5e.jpg", "s2_url": "https://s2.images.dailypics.cn/201904/e54d9316713fc1ea600f34e86a1fbe5e.jpg", "type": ".jpg", "aspect_ratio": "16:10.7", "info": {"image": {"size": 0, "format": "null"}, "exif": {}}, "size_b": 0, "size_kb": 0.0, "size_mb": 0.0, "size": "0.0KB", "p_content_html": "<p>//\u6211\u4e0e\u4f60\u7684\u5e78\u798f\u3002</p>", "if_today": false, "ago": 885, "ago_zh": "885\u5929\u524d"}