{"PID": "aa16172c-3f5a-11e9-8eca-f23c914b97eb", "p_title": "\u65e9\u5b89\u55b5", "p_content": "\u554a\u2026\u65e9\u554a\u7c73\u5a1c\u6851\uff5e  \n\u56fe\u6e90:Pixiv  \n\u521b\u4f5c\u8005\uff1amm2k  \n//\u54c8\u6b20\uff08", "width": 2508, "height": 3541, "username": "Galentwww", "p_link": "https://ws1.sinaimg.cn/large/005Yc5lzgy1g0sbyjx4q5j31xo2qde82.jpg", "local_url": "https://img.dpic.dev/b16bb7216f9443e4c69318cf2ac28138", "TID": "4ac1c07f-a9f7-11e8-a8ea-0202761b0892", "p_date": "2019-03-06", "theme_color": "#fdfeea", "text_color": "#000000", "nativePath": "/201903/b16bb7216f9443e4c69318cf2ac28138.jpg", "s1_url": "https://s1.images.dailypics.cn/201903/b16bb7216f9443e4c69318cf2ac28138.jpg", "s2_url": "https://s2.images.dailypics.cn/201903/b16bb7216f9443e4c69318cf2ac28138.jpg", "type": ".jpg", "aspect_ratio": "9:12.7", "info": {"image": {"size": 0, "format": "null"}, "exif": {}}, "size_b": 0, "size_kb": 0.0, "size_mb": 0.0, "size": "0.0KB", "p_content_html": "<p>\u554a\u2026\u65e9\u554a\u7c73\u5a1c\u6851\uff5e  <br />\n\u56fe\u6e90:Pixiv  <br />\n\u521b\u4f5c\u8005\uff1amm2k  <br />\n//\u54c8\u6b20\uff08</p>", "if_today": false, "ago": 932, "ago_zh": "932\u5929\u524d"}