[{"PID": "40f83d25-aeef-11ea-afa7-c07c56ee9ffc", "p_title": "アッシュ", "p_content": "*本图人物出自《火焰之纹章：风花雪月》  \n> 图源：[Pixiv@ゆうきりお](https://www.pixiv.net/artworks/77470101 \"Pixiv@ゆうきりお\")", "width": 750, "height": 1053, "username": "Createlite", "p_link": "https://img.dpic.dev/7c947da82478474d7c3f64a65f2820b8", "local_url": "https://img.dpic.dev/7c947da82478474d7c3f64a65f2820b8", "TID": "4ac1c07f-a9f7-11e8-a8ea-0202761b0892", "p_date": "2020-06-16", "theme_color": "#f2ecea", "text_color": "#000000", "nativePath": "/202006/7c947da82478474d7c3f64a65f2820b8.jpg", "s1_url": "https://s1.images.dailypics.cn/202006/7c947da82478474d7c3f64a65f2820b8.jpg", "s2_url": "https://s2.images.dailypics.cn/202006/7c947da82478474d7c3f64a65f2820b8.jpg", "type": ".jpg", "aspect_ratio": "9:12.6", "info": {"image": {"size": 0, "format": "null"}, "exif": {}}, "size_b": 0, "size_kb": 0.0, "size_mb": 0.0, "size": "0.0KB", "p_content_html": "<p>*本图人物出自《火焰之纹章：风花雪月》    </p>\n<blockquote>\n<p>图源：<a href=\"https://www.pixiv.net/artworks/77470101\" title=\"Pixiv@ゆうきりお\">Pixiv@ゆうきりお</a></p>\n</blockquote>", "if_today": false, "ago": 493, "ago_zh": "493天前"}, {"PID": "50f06a1e-849b-11ea-8f08-0202761b0196", "p_title": "Daisy", "p_content": "明眸之中，可见星辰。  \n~~不是星尘，真的~~  \n> 图源：[Pixiv@MECHURAGI](https://www.pixiv.net/artworks/72179030)", "width": 645, "height": 900, "username": "Galentwww", "p_link": "https://img.dpic.dev/c9f2646fceec7e5eb521344e38fe71d3", "local_url": "https://img.dpic.dev/c9f2646fceec7e5eb521344e38fe71d3", "TID": "4ac1c07f-a9f7-11e8-a8ea-0202761b0892", "p_date": "2020-04-23", "theme_color": "#222944", "text_color": "#ffffff", "nativePath": "/202004/c9f2646fceec7e5eb521344e38fe71d3.png", "s1_url": "https://s1.images.dailypics.cn/202004/c9f2646fceec7e5eb521344e38fe71d3.png", "s2_url": "https://s2.images.dailypics.cn/202004/c9f2646fceec7e5eb521344e38fe71d3.png", "type": ".png", "aspect_ratio": "9:12.6", "info": {"image": {"size": 0, "format": "null"}, "exif": {}}, "size_b": 0, "size_kb": 0.0, "size_mb": 0.0, "size": "0.0KB", "p_content_html": "<p>明眸之中，可见星辰。  <br />\n<del>不是星尘，真的</del>    </p>\n<blockquote>\n<p>图源：<a href=\"https://www.pixiv.net/artworks/72179030\">Pixiv@MECHURAGI</a></p>\n</blockquote>", "if_today": false, "ago": 547, "ago_zh": "547天前"}, {"PID": "ac0bf8ca-8249-11ea-8f08-0202761b0196", "p_title": "公主连结 Re.Dive", "p_content": "在 4 月 17 日，《公主连结 Re.Dive》 以一个极其奇妙的推广方式在国内正式开服——代理商为 Bilibili  \n// 如果我不说，你们知道接头霸王的角色名叫凯露吗  \n> 图源：[Pixiv@ナナセミオリ](https://www.pixiv.net/artworks/80860383)", "width": 858, "height": 1200, "username": "Galentwww", "p_link": "https://img.dpic.dev/dd638b6cb7bd7e53e7d2505b1e2e4003", "local_url": "https://img.dpic.dev/dd638b6cb7bd7e53e7d2505b1e2e4003", "TID": "4ac1c07f-a9f7-11e8-a8ea-0202761b0892", "p_date": "2020-04-20", "theme_color": "#fdf3f8", "text_color": "#000000", "nativePath": "/202004/dd638b6cb7bd7e53e7d2505b1e2e4003.jpg", "s1_url": "https://s1.images.dailypics.cn/202004/dd638b6cb7bd7e53e7d2505b1e2e4003.jpg", "s2_url": "https://s2.images.dailypics.cn/202004/dd638b6cb7bd7e53e7d2505b1e2e4003.jpg", "type": ".jpg", "aspect_ratio": "9:12.6", "info": {"image": {"size": 0, "format": "null"}, "exif": {}}, "size_b": 0, "size_kb": 0.0, "size_mb": 0.0, "size": "0.0KB", "p_content_html": "<p>在 4 月 17 日，《公主连结 Re.Dive》 以一个极其奇妙的推广方式在国内正式开服——代理商为 Bilibili  <br />\n// 如果我不说，你们知道接头霸王的角色名叫凯露吗    </p>\n<blockquote>\n<p>图源：<a href=\"https://www.pixiv.net/artworks/80860383\">Pixiv@ナナセミオリ</a></p>\n</blockquote>", "if_today": false, "ago": 550, "ago_zh": "550天前"}, {"PID": "5bdeab4e-620d-11ea-8f08-0202761b0196", "p_title": "狐狸姐姐好可爱", "p_content": "Youtube 白上吹雪订阅者超过 300000 人祝贺！  \n> 图源:[Pixiv@.suke@お仕事募集中](https://www.pixiv.net/artworks/78410037)", "width": 3885, "height": 5436, "username": "QHATY", "p_link": "https://img.dpic.dev/0ed56736e88d662b9ef3dafb4f3a632a", "local_url": "https://img.dpic.dev/0ed56736e88d662b9ef3dafb4f3a632a", "TID": "4ac1c07f-a9f7-11e8-a8ea-0202761b0892", "p_date": "2020-03-10", "theme_color": "#fffffa", "text_color": "#000000", "nativePath": "/202003/0ed56736e88d662b9ef3dafb4f3a632a.png", "s1_url": "https://s1.images.dailypics.cn/202003/0ed56736e88d662b9ef3dafb4f3a632a.png", "s2_url": "https://s2.images.dailypics.cn/202003/0ed56736e88d662b9ef3dafb4f3a632a.png", "type": ".png", "aspect_ratio": "9:12.6", "info": {"image": {"size": 0, "format": "null"}, "exif": {}}, "size_b": 0, "size_kb": 0.0, "size_mb": 0.0, "size": "0.0KB", "p_content_html": "<p>Youtube 白上吹雪订阅者超过 300000 人祝贺！    </p>\n<blockquote>\n<p>图源:<a href=\"https://www.pixiv.net/artworks/78410037\">Pixiv@.suke@お仕事募集中</a></p>\n</blockquote>", "if_today": false, "ago": 591, "ago_zh": "591天前"}, {"PID": "504560ef-3e74-11ea-9f69-0202761b0196", "p_title": "謹賀新年 2020", "p_content": "先預祝大家2020鼠年行大運，農曆新年快樂  \n期望2020是和平的一年 ^_^  \n  \n图源：[Pixiv#79056163](https://www.pixiv.net/artworks/79056163 \"Pixiv#79056163\")  \n画师：上条(Lac)", "width": 1433, "height": 2000, "username": "KFC0803", "p_link": "https://img.dpic.dev/1db7a1bc72e8b436518bf47b20fe1205", "local_url": "https://img.dpic.dev/1db7a1bc72e8b436518bf47b20fe1205", "TID": "4ac1c07f-a9f7-11e8-a8ea-0202761b0892", "p_date": "2020-01-24", "theme_color": "#f5efe6", "text_color": "#000000", "nativePath": "/202001/1db7a1bc72e8b436518bf47b20fe1205.jpg", "s1_url": "https://s1.images.dailypics.cn/202001/1db7a1bc72e8b436518bf47b20fe1205.jpg", "s2_url": "https://s2.images.dailypics.cn/202001/1db7a1bc72e8b436518bf47b20fe1205.jpg", "type": ".jpg", "aspect_ratio": "9:12.6", "info": {"image": {"size": 0, "format": "null"}, "exif": {}}, "size_b": 0, "size_kb": 0.0, "size_mb": 0.0, "size": "0.0KB", "p_content_html": "<p>先預祝大家2020鼠年行大運，農曆新年快樂  <br />\n期望2020是和平的一年 ^_^    </p>\n<p>图源：<a href=\"https://www.pixiv.net/artworks/79056163\" title=\"Pixiv#79056163\">Pixiv#79056163</a>  <br />\n画师：上条(Lac)</p>", "if_today": false, "ago": 637, "ago_zh": "637天前"}, {"PID": "cf8c17cd-d3d9-11e9-93b5-f23c914b97eb", "p_title": "猫耳", "p_content": "图源：Pixiv#76596270  \n画师：リン☆ユウ  \n//猫耳什么的最棒了 尤其是看傲娇带着猫耳！", "width": 936, "height": 1307, "username": "Createlite", "p_link": "https://img.dpic.dev/283da48aa1a20eb65ddd5559a5844b0a", "local_url": "https://img.dpic.dev/283da48aa1a20eb65ddd5559a5844b0a", "TID": "4ac1c07f-a9f7-11e8-a8ea-0202761b0892", "p_date": "2019-09-11", "theme_color": "#d5d1ce", "text_color": "#000000", "nativePath": "/201909/283da48aa1a20eb65ddd5559a5844b0a.png", "s1_url": "https://s1.images.dailypics.cn/201909/283da48aa1a20eb65ddd5559a5844b0a.png", "s2_url": "https://s2.images.dailypics.cn/201909/283da48aa1a20eb65ddd5559a5844b0a.png", "type": ".png", "aspect_ratio": "9:12.6", "info": {"image": {"size": 0, "format": "null"}, "exif": {}}, "size_b": 0, "size_kb": 0.0, "size_mb": 0.0, "size": "0.0KB", "p_content_html": "<p>图源：Pixiv#76596270  <br />\n画师：リン☆ユウ  <br />\n//猫耳什么的最棒了 尤其是看傲娇带着猫耳！</p>", "if_today": false, "ago": 772, "ago_zh": "772天前"}, {"PID": "63493bf5-cf1f-11e9-93b5-f23c914b97eb", "p_title": "もうすぐ夏休み", "p_content": "图源：Pixiv#75706536  \n画师：森倉円  \n//看了一下图片元素：裸足、女子高生、美少女、夏日天空、制服  \n  \n仔细想想 夏天马上就过去了，不知道诸位有没有在夏天去海边旅行呢？  \n（PS：本图也收录在了 森倉円 的夏季单行本中）", "width": 1191, "height": 1670, "username": "Createlite", "p_link": "https://img.dpic.dev/9ed8fd5b0e452d759770e79da000f554", "local_url": "https://img.dpic.dev/9ed8fd5b0e452d759770e79da000f554", "TID": "4ac1c07f-a9f7-11e8-a8ea-0202761b0892", "p_date": "2019-09-05", "theme_color": "#dbf7fe", "text_color": "#000000", "nativePath": "/201909/9ed8fd5b0e452d759770e79da000f554.png", "s1_url": "https://s1.images.dailypics.cn/201909/9ed8fd5b0e452d759770e79da000f554.png", "s2_url": "https://s2.images.dailypics.cn/201909/9ed8fd5b0e452d759770e79da000f554.png", "type": ".png", "aspect_ratio": "9:12.6", "info": {"image": {"size": 0, "format": "null"}, "exif": {}}, "size_b": 0, "size_kb": 0.0, "size_mb": 0.0, "size": "0.0KB", "p_content_html": "<p>图源：Pixiv#75706536  <br />\n画师：森倉円  <br />\n//看了一下图片元素：裸足、女子高生、美少女、夏日天空、制服    </p>\n<p>仔细想想 夏天马上就过去了，不知道诸位有没有在夏天去海边旅行呢？  <br />\n（PS：本图也收录在了 森倉円 的夏季单行本中）</p>", "if_today": false, "ago": 778, "ago_zh": "778天前"}, {"PID": "5050c144-afba-11e9-93b5-f23c914b97eb", "p_title": "金魚と浴衣と風鈴と", "p_content": "图源：Pixiv  \n画师：望月しいな  \nPID：70028779  \n//金鱼浴衣？太可爱了吧...头上的花朵和画作两旁的金鱼...", "width": 2110, "height": 2961, "username": "Createlite", "p_link": "https://img.dpic.dev/b375ae804fefd1a8d13c8d076490c6b0", "local_url": "https://img.dpic.dev/b375ae804fefd1a8d13c8d076490c6b0", "TID": "4ac1c07f-a9f7-11e8-a8ea-0202761b0892", "p_date": "2019-07-27", "theme_color": "#d9ebf0", "text_color": "#000000", "nativePath": "/201907/b375ae804fefd1a8d13c8d076490c6b0.jpg", "s1_url": "https://s1.images.dailypics.cn/201907/b375ae804fefd1a8d13c8d076490c6b0.jpg", "s2_url": "https://s2.images.dailypics.cn/201907/b375ae804fefd1a8d13c8d076490c6b0.jpg", "type": ".jpg", "aspect_ratio": "9:12.6", "info": {"image": {"size": 0, "format": "null"}, "exif": {}}, "size_b": 0, "size_kb": 0.0, "size_mb": 0.0, "size": "0.0KB", "p_content_html": "<p>图源：Pixiv  <br />\n画师：望月しいな  <br />\nPID：70028779  <br />\n//金鱼浴衣？太可爱了吧...头上的花朵和画作两旁的金鱼...</p>", "if_today": false, "ago": 818, "ago_zh": "818天前"}, {"PID": "c7f6550a-6838-11e9-ace4-f23c914b97eb", "p_title": "艦これ六周年 · 贺", "p_content": "准备好了吗？在拂晓的水平线上刻下胜利吧！  \n图源：Pixiv @順葉やしろ  \n//祝！艦これ6周年！", "width": 1117, "height": 1568, "username": "Galentwww", "p_link": "https://i.loli.net/2019/04/26/5cc323b8d217b.jpg", "local_url": "https://img.dpic.dev/b2d778c645b5c5fd19a7acca69bf4129", "TID": "4ac1c07f-a9f7-11e8-a8ea-0202761b0892", "p_date": "2019-04-27", "theme_color": "#fcf3f4", "text_color": "#000000", "nativePath": "/201904/b2d778c645b5c5fd19a7acca69bf4129.jpg", "s1_url": "https://s1.images.dailypics.cn/201904/b2d778c645b5c5fd19a7acca69bf4129.jpg", "s2_url": "https://s2.images.dailypics.cn/201904/b2d778c645b5c5fd19a7acca69bf4129.jpg", "type": ".jpg", "aspect_ratio": "9:12.6", "info": {"image": {"size": 0, "format": "null"}, "exif": {}}, "size_b": 0, "size_kb": 0.0, "size_mb": 0.0, "size": "0.0KB", "p_content_html": "<p>准备好了吗？在拂晓的水平线上刻下胜利吧！  <br />\n图源：Pixiv @順葉やしろ  <br />\n//祝！艦これ6周年！</p>", "if_today": false, "ago": 909, "ago_zh": "909天前"}, {"PID": "ff037588-65e1-11e9-a958-f23c914b97eb", "p_title": "おはよ", "p_content": "Pixiv ID：74114465  \n画师：森倉円  \n//春日里的制服少女（话说，沈阳的花季已经过了...期待明年吧！）", "width": 1036, "height": 1450, "username": "Createlite", "p_link": "https://ws3.sinaimg.cn/large/005SeDP8gy1g2d0ltgvh6j30ss14a1ky.jpg", "local_url": "https://img.dpic.dev/6db9100809e93ea90aa9115e4fb7ab9c", "TID": "4ac1c07f-a9f7-11e8-a8ea-0202761b0892", "p_date": "2019-04-26", "theme_color": "#f8f3f4", "text_color": "#000000", "nativePath": "/201904/6db9100809e93ea90aa9115e4fb7ab9c.jpg", "s1_url": "https://s1.images.dailypics.cn/201904/6db9100809e93ea90aa9115e4fb7ab9c.jpg", "s2_url": "https://s2.images.dailypics.cn/201904/6db9100809e93ea90aa9115e4fb7ab9c.jpg", "type": ".jpg", "aspect_ratio": "9:12.6", "info": {"image": {"size": 0, "format": "null"}, "exif": {}}, "size_b": 0, "size_kb": 0.0, "size_mb": 0.0, "size": "0.0KB", "p_content_html": "<p>Pixiv ID：74114465  <br />\n画师：森倉円  <br />\n//春日里的制服少女（话说，沈阳的花季已经过了...期待明年吧！）</p>", "if_today": false, "ago": 910, "ago_zh": "910天前"}, {"PID": "4f0e74d3-4bdb-11e9-8eca-f23c914b97eb", "p_title": "真乃", "p_content": "//花嫁，应该是最美的服装了吧  \n#アイドルマスターシャイニーカラーズ偶像大师 闪耀色彩  \n图源：Pixiv 73792834  \n创作者：木なこ@お仕事募集中", "width": 1190, "height": 1670, "username": "Galentwww", "p_link": "https://ws3.sinaimg.cn/large/005BYqpgly1g2gjjx1coij30u01641ky.jpg", "local_url": "https://img.dpic.dev/1b95a903bf92825dd40c3dc35c585ce0", "TID": "4ac1c07f-a9f7-11e8-a8ea-0202761b0892", "p_date": "2019-03-22", "theme_color": "#fcf3ee", "text_color": "#000000", "nativePath": "/201903/1b95a903bf92825dd40c3dc35c585ce0.jpg", "s1_url": "https://s1.images.dailypics.cn/201903/1b95a903bf92825dd40c3dc35c585ce0.jpg", "s2_url": "https://s2.images.dailypics.cn/201903/1b95a903bf92825dd40c3dc35c585ce0.jpg", "type": ".jpg", "aspect_ratio": "9:12.6", "info": {"image": {"size": 0, "format": "null"}, "exif": {}}, "size_b": 0, "size_kb": 0.0, "size_mb": 0.0, "size": "0.0KB", "p_content_html": "<p>//花嫁，应该是最美的服装了吧    </p>\n<h1>アイドルマスターシャイニーカラーズ偶像大师 闪耀色彩</h1>\n<p>图源：Pixiv 73792834  <br />\n创作者：木なこ@お仕事募集中</p>", "if_today": false, "ago": 945, "ago_zh": "945天前"}, {"PID": "f875d387-4567-11e9-8eca-f23c914b97eb", "p_title": "Kizuna Ai", "p_content": "这个zz竟该死的甜美.JPG  \n图源：Pixiv  \n创作者：森倉円", "width": 1036, "height": 1450, "username": "tanyinyouxi", "p_link": "https://ws1.sinaimg.cn/large/005SeDP8gy1g116sgkh9xj30ss14ae4k.jpg", "local_url": "https://img.dpic.dev/ff4fe76ce1baed3d57d4af8dfbdd441b", "TID": "4ac1c07f-a9f7-11e8-a8ea-0202761b0892", "p_date": "2019-03-15", "theme_color": "#fabed5", "text_color": "#000000", "nativePath": "/201903/ff4fe76ce1baed3d57d4af8dfbdd441b.jpg", "s1_url": "https://s1.images.dailypics.cn/201903/ff4fe76ce1baed3d57d4af8dfbdd441b.jpg", "s2_url": "https://s2.images.dailypics.cn/201903/ff4fe76ce1baed3d57d4af8dfbdd441b.jpg", "type": ".jpg", "aspect_ratio": "9:12.6", "info": {"image": {"size": 0, "format": "null"}, "exif": {}}, "size_b": 0, "size_kb": 0.0, "size_mb": 0.0, "size": "0.0KB", "p_content_html": "<p>这个zz竟该死的甜美.JPG  <br />\n图源：Pixiv  <br />\n创作者：森倉円</p>", "if_today": false, "ago": 952, "ago_zh": "952天前"}, {"PID": "9c1ac307-2e5b-11e9-a900-0202761b0892", "p_title": "「何お願いしたの？」って？ ……内緒。", "p_content": "祈愿楼上变成妹子.jpg  \n创作者：necömi@3日目東A18a  \n图源：Pixiv 72318833  \n投稿：浅知若忆  \n//何以解忧，唯有暴富XDDDD", "width": 1000, "height": 1396, "username": "Galentwww", "p_link": "https://ws1.sinaimg.cn/large/005Yc5lzly1g04ipofje7j30rs12swlj.jpg", "local_url": "https://img.dpic.dev/bef24fc9647bc121d0224b6536e6d7a3", "TID": "4ac1c07f-a9f7-11e8-a8ea-0202761b0892", "p_date": "2019-02-12", "theme_color": "#48506e", "text_color": "#ffffff", "nativePath": "/201902/bef24fc9647bc121d0224b6536e6d7a3.jpg", "s1_url": "https://s1.images.dailypics.cn/201902/bef24fc9647bc121d0224b6536e6d7a3.jpg", "s2_url": "https://s2.images.dailypics.cn/201902/bef24fc9647bc121d0224b6536e6d7a3.jpg", "type": ".jpg", "aspect_ratio": "9:12.6", "info": {"image": {"size": 0, "format": "null"}, "exif": {}}, "size_b": 0, "size_kb": 0.0, "size_mb": 0.0, "size": "0.0KB", "p_content_html": "<p>祈愿楼上变成妹子.jpg  <br />\n创作者：necömi@3日目東A18a  <br />\n图源：Pixiv 72318833  <br />\n投稿：浅知若忆  <br />\n//何以解忧，唯有暴富XDDDD</p>", "if_today": false, "ago": 983, "ago_zh": "983天前"}, {"PID": "f9cdc587-1731-11e9-8236-0202761b0892", "p_title": "学生会长", "p_content": "画师：ミア  \n图源：Pixiv  \n插画ID：72603304", "width": 1460, "height": 2048, "username": "Createlite", "p_link": "https://ws1.sinaimg.cn/large/006N1muNly1fz58z8fb7qj314k1kwk2r.jpg", "local_url": "https://img.dpic.dev/a86e2490666d34fc5396f37977132c3f", "TID": "4ac1c07f-a9f7-11e8-a8ea-0202761b0892", "p_date": "2019-01-14", "theme_color": "#ece3df", "text_color": "#000000", "nativePath": "/201901/a86e2490666d34fc5396f37977132c3f.jpg", "s1_url": "https://s1.images.dailypics.cn/201901/a86e2490666d34fc5396f37977132c3f.jpg", "s2_url": "https://s2.images.dailypics.cn/201901/a86e2490666d34fc5396f37977132c3f.jpg", "type": ".jpg", "aspect_ratio": "9:12.6", "info": {"image": {"size": 0, "format": "null"}, "exif": {}}, "size_b": 0, "size_kb": 0.0, "size_mb": 0.0, "size": "0.0KB", "p_content_html": "<p>画师：ミア  <br />\n图源：Pixiv  <br />\n插画ID：72603304</p>", "if_today": false, "ago": 1012, "ago_zh": "1012天前"}, {"PID": "ae04c4c9-ab97-11e8-a8ea-0202761b0892", "p_title": "冬服シロちゃん", "p_content": "今天很火的虚拟 Youtuber ，有人知道是谁么～  \n出处：Pixiv 70013759  \n作者：チノマロン@2日目西め-15b  \n作者 Twitter ：@chinomaron  \n其实人家叫 Siro 啦", "width": 1072, "height": 1500, "username": "Createlite", "p_link": "https://ws3.sinaimg.cn/large/0069RVTdly1fu0b80guj3j30ts15o7wh.jpg", "local_url": "https://img.dpic.dev/f403f66f52c81945c499f226bc6a8ab5", "TID": "4ac1c07f-a9f7-11e8-a8ea-0202761b0892", "p_date": "2018-08-07", "theme_color": "#374587", "text_color": "#ffffff", "nativePath": "/201808/f403f66f52c81945c499f226bc6a8ab5.jpg", "s1_url": "https://s1.images.dailypics.cn/201808/f403f66f52c81945c499f226bc6a8ab5.jpg", "s2_url": "https://s2.images.dailypics.cn/201808/f403f66f52c81945c499f226bc6a8ab5.jpg", "type": ".jpg", "aspect_ratio": "9:12.6", "info": {"image": {"size": 0, "format": "null"}, "exif": {}}, "size_b": 0, "size_kb": 0.0, "size_mb": 0.0, "size": "0.0KB", "p_content_html": "<p>今天很火的虚拟 Youtuber ，有人知道是谁么～  <br />\n出处：Pixiv 70013759  <br />\n作者：チノマロン@2日目西め-15b  <br />\n作者 Twitter ：@chinomaron  <br />\n其实人家叫 Siro 啦</p>", "if_today": false, "ago": 1172, "ago_zh": "1172天前"}, {"PID": "bfd3e77b-640c-11ea-8f08-0202761b0196", "p_title": "万象天地", "p_content": "万象天地，色彩斑斓  \n> 图源：Dailypicd@Shanon  \n> 拍摄器材：Redmi Note 4 f/2.0 with Snapseed  \n> 拍摄地：深圳市，广东省", "width": 3027, "height": 4224, "username": "Shanon", "p_link": "https://img.dpic.dev/3439eefb8f8ac99ee0804de18986ec59", "local_url": "https://img.dpic.dev/3439eefb8f8ac99ee0804de18986ec59", "TID": "5398f27b-a9f7-11e8-a8ea-0202761b0892", "p_date": "2020-03-13", "theme_color": "#5f5462", "text_color": "#ffffff", "nativePath": "/202003/3439eefb8f8ac99ee0804de18986ec59.jpg", "s1_url": "https://s1.images.dailypics.cn/202003/3439eefb8f8ac99ee0804de18986ec59.jpg", "s2_url": "https://s2.images.dailypics.cn/202003/3439eefb8f8ac99ee0804de18986ec59.jpg", "type": ".jpg", "aspect_ratio": "9:12.6", "info": {"image": {"size": 0, "format": "null"}, "exif": {}}, "size_b": 0, "size_kb": 0.0, "size_mb": 0.0, "size": "0.0KB", "p_content_html": "<p>万象天地，色彩斑斓    </p>\n<blockquote>\n<p>图源：Dailypicd@Shanon  <br />\n拍摄器材：Redmi Note 4 f/2.0 with Snapseed  <br />\n拍摄地：深圳市，广东省</p>\n</blockquote>", "if_today": false, "ago": 588, "ago_zh": "588天前"}]