[{"PID": "e4fed3c8-18e7-11ea-a93e-0202761b0196", "p_title": "霜星", "p_content": "喜欢这种飘渺的图，宁静致远。  \n  \n//图源：Pixiv#78137782  \n画师：zzz", "width": 1080, "height": 2160, "username": "Createlite", "p_link": "https://img.dpic.dev/ab65b4e1e168d74827a07da6fd94a284", "local_url": "https://img.dpic.dev/ab65b4e1e168d74827a07da6fd94a284", "TID": "4ac1c07f-a9f7-11e8-a8ea-0202761b0892", "p_date": "2019-12-08", "theme_color": "#809eb2", "text_color": "#000000", "nativePath": "/201912/ab65b4e1e168d74827a07da6fd94a284.jpg", "s1_url": "https://s1.images.dailypics.cn/201912/ab65b4e1e168d74827a07da6fd94a284.jpg", "s2_url": "https://s2.images.dailypics.cn/201912/ab65b4e1e168d74827a07da6fd94a284.jpg", "type": ".jpg", "aspect_ratio": "1:2", "info": {"image": {"size": 0, "format": "null"}, "exif": {}}, "size_b": 0, "size_kb": 0.0, "size_mb": 0.0, "size": "0.0KB", "p_content_html": "<p>喜欢这种飘渺的图，宁静致远。    </p>\n<p>//图源：Pixiv#78137782  <br />\n画师：zzz</p>", "if_today": false, "ago": 836, "ago_zh": "836天前"}, {"PID": "b3d38d32-0df4-11ea-a93e-0202761b0196", "p_title": "少女、旅行", "p_content": "少女的心事本来就是难以捉摸的，所以，不要尝试搞明白少女究竟在想些什么  \n图源：Pixiv# 77898133  \n画师: 爽々", "width": 1080, "height": 2160, "username": "Createlite", "p_link": "https://img.dpic.dev/65b4a1c00b563d02a2e69c2547820dae", "local_url": "https://img.dpic.dev/65b4a1c00b563d02a2e69c2547820dae", "TID": "4ac1c07f-a9f7-11e8-a8ea-0202761b0892", "p_date": "2019-11-24", "theme_color": "#6181a2", "text_color": "#000000", "nativePath": "/201911/65b4a1c00b563d02a2e69c2547820dae.jpg", "s1_url": "https://s1.images.dailypics.cn/201911/65b4a1c00b563d02a2e69c2547820dae.jpg", "s2_url": "https://s2.images.dailypics.cn/201911/65b4a1c00b563d02a2e69c2547820dae.jpg", "type": ".jpg", "aspect_ratio": "1:2", "info": {"image": {"size": 0, "format": "null"}, "exif": {}}, "size_b": 0, "size_kb": 0.0, "size_mb": 0.0, "size": "0.0KB", "p_content_html": "<p>少女的心事本来就是难以捉摸的，所以，不要尝试搞明白少女究竟在想些什么  <br />\n图源：Pixiv# 77898133  <br />\n画师: 爽々</p>", "if_today": false, "ago": 850, "ago_zh": "850天前"}, {"PID": "447ae296-79e4-11e9-9337-f23c914b97eb", "p_title": "Rem", "p_content": "Pixiv ID: 74530542  \n画师:やすゆき  \n采花的 Rem 还是这么好看呢  \n这个画师画的其他的雷姆插画都色色的…  \n// 反正 520 也到了，就给你们一个老婆用用算了 XD", "width": 1080, "height": 2160, "username": "RyanQwQ", "p_link": "https://img.dpic.dev/3f1b3c1bc44293149835f49cbd7d92ca", "local_url": "https://img.dpic.dev/3f1b3c1bc44293149835f49cbd7d92ca", "TID": "4ac1c07f-a9f7-11e8-a8ea-0202761b0892", "p_date": "2019-05-20", "theme_color": "#f5ecec", "text_color": "#000000", "nativePath": "/201905/3f1b3c1bc44293149835f49cbd7d92ca.jpg", "s1_url": "https://s1.images.dailypics.cn/201905/3f1b3c1bc44293149835f49cbd7d92ca.jpg", "s2_url": "https://s2.images.dailypics.cn/201905/3f1b3c1bc44293149835f49cbd7d92ca.jpg", "type": ".jpg", "aspect_ratio": "1:2", "info": {"image": {"size": 0, "format": "null"}, "exif": {}}, "size_b": 0, "size_kb": 0.0, "size_mb": 0.0, "size": "0.0KB", "p_content_html": "<p>Pixiv ID: 74530542  <br />\n画师:やすゆき  <br />\n采花的 Rem 还是这么好看呢  <br />\n这个画师画的其他的雷姆插画都色色的…  <br />\n// 反正 520 也到了，就给你们一个老婆用用算了 XD</p>", "if_today": false, "ago": 1038, "ago_zh": "1038天前"}, {"PID": "f19c6ccc-5d15-11e9-a958-f23c914b97eb", "p_title": "纳闷", "p_content": "图源：Tujian 投稿  \n//If I never see you again, good morning, good afternoon, good night.   \n如果再也不能见到你，祝你早安，午安，晚安。  \n//好有诗意的一言，来加入我们运营组吧XD", "width": 1080, "height": 2160, "username": "流口水的兔子", "p_link": "https://ws3.sinaimg.cn/large/005SeDP8gy1g1yoibjsw7j30u01o0mzq.jpg", "local_url": "https://img.dpic.dev/c07079f5f0df2e38ac7292ed5a114ff4", "TID": "4ac1c07f-a9f7-11e8-a8ea-0202761b0892", "p_date": "2019-04-14", "theme_color": "#a2a0ad", "text_color": "#000000", "nativePath": "/201904/c07079f5f0df2e38ac7292ed5a114ff4.jpg", "s1_url": "https://s1.images.dailypics.cn/201904/c07079f5f0df2e38ac7292ed5a114ff4.jpg", "s2_url": "https://s2.images.dailypics.cn/201904/c07079f5f0df2e38ac7292ed5a114ff4.jpg", "type": ".jpg", "aspect_ratio": "1:2", "info": {"image": {"size": 0, "format": "null"}, "exif": {}}, "size_b": 0, "size_kb": 0.0, "size_mb": 0.0, "size": "0.0KB", "p_content_html": "<p>图源：Tujian 投稿  <br />\n//If I never see you again, good morning, good afternoon, good night.   <br />\n如果再也不能见到你，祝你早安，午安，晚安。  <br />\n//好有诗意的一言，来加入我们运营组吧XD</p>", "if_today": false, "ago": 1074, "ago_zh": "1074天前"}, {"PID": "f661e752-57b8-11e9-a958-f23c914b97eb", "p_title": "樱花与和服", "p_content": "好可爱的画风...樱花与和服少女的搭配...  \n//图片讯息：  \nP站画师ID：あやみ  \n作品ID：74045348", "width": 1080, "height": 2160, "username": "Createlite", "p_link": "https://ws3.sinaimg.cn/large/005SeDP8gy1g1s6mq0h6vj30u01o0kjl.jpg", "local_url": "https://img.dpic.dev/9074fc02ecebc161c87b7cb5fbafaf09", "TID": "4ac1c07f-a9f7-11e8-a8ea-0202761b0892", "p_date": "2019-04-06", "theme_color": "#f8ebea", "text_color": "#000000", "nativePath": "/201904/9074fc02ecebc161c87b7cb5fbafaf09.jpg", "s1_url": "https://s1.images.dailypics.cn/201904/9074fc02ecebc161c87b7cb5fbafaf09.jpg", "s2_url": "https://s2.images.dailypics.cn/201904/9074fc02ecebc161c87b7cb5fbafaf09.jpg", "type": ".jpg", "aspect_ratio": "1:2", "info": {"image": {"size": 0, "format": "null"}, "exif": {}}, "size_b": 0, "size_kb": 0.0, "size_mb": 0.0, "size": "0.0KB", "p_content_html": "<p>好可爱的画风...樱花与和服少女的搭配...  <br />\n//图片讯息：  <br />\nP站画师ID：あやみ  <br />\n作品ID：74045348</p>", "if_today": false, "ago": 1082, "ago_zh": "1082天前"}, {"PID": "b4accd1a-56f4-11e9-a958-f23c914b97eb", "p_title": "杂图", "p_content": "图源：酷安  \n//樱花飞舞的四月，会发生什么事情呢？", "width": 1080, "height": 2160, "username": "Createlite", "p_link": "https://ws1.sinaimg.cn/large/005SeDP8gy1g1r1y6n415j30u01o04qp.jpg", "local_url": "https://img.dpic.dev/2296940f272d3b6e524c44c1233e2e54", "TID": "4ac1c07f-a9f7-11e8-a8ea-0202761b0892", "p_date": "2019-04-05", "theme_color": "#f0e4e7", "text_color": "#000000", "nativePath": "/201904/2296940f272d3b6e524c44c1233e2e54.jpg", "s1_url": "https://s1.images.dailypics.cn/201904/2296940f272d3b6e524c44c1233e2e54.jpg", "s2_url": "https://s2.images.dailypics.cn/201904/2296940f272d3b6e524c44c1233e2e54.jpg", "type": ".jpg", "aspect_ratio": "1:2", "info": {"image": {"size": 0, "format": "null"}, "exif": {}}, "size_b": 0, "size_kb": 0.0, "size_mb": 0.0, "size": "0.0KB", "p_content_html": "<p>图源：酷安  <br />\n//樱花飞舞的四月，会发生什么事情呢？</p>", "if_today": false, "ago": 1083, "ago_zh": "1083天前"}, {"PID": "011a4433-4b2e-11e9-8eca-f23c914b97eb", "p_title": "少女", "p_content": "//一人静坐的少女。", "width": 1440, "height": 2880, "username": "Createlite", "p_link": "https://i.loli.net/2019/04/27/5cc331b77d36c.png", "local_url": "https://img.dpic.dev/37cd5dd3975d5d5e2c67ae26e94c6a10", "TID": "4ac1c07f-a9f7-11e8-a8ea-0202761b0892", "p_date": "2019-03-21", "theme_color": "#b3b8be", "text_color": "#000000", "nativePath": "/201903/37cd5dd3975d5d5e2c67ae26e94c6a10.jpg", "s1_url": "https://s1.images.dailypics.cn/201903/37cd5dd3975d5d5e2c67ae26e94c6a10.jpg", "s2_url": "https://s2.images.dailypics.cn/201903/37cd5dd3975d5d5e2c67ae26e94c6a10.jpg", "type": ".jpg", "aspect_ratio": "1:2", "info": {"image": {"size": 0, "format": "null"}, "exif": {}}, "size_b": 0, "size_kb": 0.0, "size_mb": 0.0, "size": "0.0KB", "p_content_html": "<p>//一人静坐的少女。</p>", "if_today": false, "ago": 1098, "ago_zh": "1098天前"}, {"PID": "bbc5cf8e-47e8-11e9-8eca-f23c914b97eb", "p_title": "拉芙塔莉雅", "p_content": "盾之勇者成名录。  \n//话说补上小说发现根本停不下来啊...", "width": 1080, "height": 2160, "username": "Createlite", "p_link": "https://ws2.sinaimg.cn/large/005SeDP8gy1g14x35vdvpj30u01o0npd.jpg", "local_url": "https://img.dpic.dev/d32a778f0abe3c391cd362ad089d1f74", "TID": "4ac1c07f-a9f7-11e8-a8ea-0202761b0892", "p_date": "2019-03-17", "theme_color": "#aadafe", "text_color": "#000000", "nativePath": "/201903/d32a778f0abe3c391cd362ad089d1f74.jpg", "s1_url": "https://s1.images.dailypics.cn/201903/d32a778f0abe3c391cd362ad089d1f74.jpg", "s2_url": "https://s2.images.dailypics.cn/201903/d32a778f0abe3c391cd362ad089d1f74.jpg", "type": ".jpg", "aspect_ratio": "1:2", "info": {"image": {"size": 0, "format": "null"}, "exif": {}}, "size_b": 0, "size_kb": 0.0, "size_mb": 0.0, "size": "0.0KB", "p_content_html": "<p>盾之勇者成名录。  <br />\n//话说补上小说发现根本停不下来啊...</p>", "if_today": false, "ago": 1102, "ago_zh": "1102天前"}, {"PID": "467735bc-3073-11e9-839c-0202761b0892", "p_title": "Maki", "p_content": "//情人节已经过去了，你是否收到礼物了呢？", "width": 2160, "height": 4320, "username": "Createlite", "p_link": "https://ws3.sinaimg.cn/large/006N1muNly1g06ejl5aygj31o03c01gk.jpg", "local_url": "https://img.dpic.dev/7b824c600307558ff138d4cc171808b6", "TID": "4ac1c07f-a9f7-11e8-a8ea-0202761b0892", "p_date": "2019-02-15", "theme_color": "#3a5944", "text_color": "#ffffff", "nativePath": "/201902/7b824c600307558ff138d4cc171808b6.jpg", "s1_url": "https://s1.images.dailypics.cn/201902/7b824c600307558ff138d4cc171808b6.jpg", "s2_url": "https://s2.images.dailypics.cn/201902/7b824c600307558ff138d4cc171808b6.jpg", "type": ".jpg", "aspect_ratio": "1:2", "info": {"image": {"size": 0, "format": "null"}, "exif": {}}, "size_b": 0, "size_kb": 0.0, "size_mb": 0.0, "size": "0.0KB", "p_content_html": "<p>//情人节已经过去了，你是否收到礼物了呢？</p>", "if_today": false, "ago": 1132, "ago_zh": "1132天前"}, {"PID": "b7228b13-0c97-11e9-b158-0202761b0892", "p_title": "杂图", "p_content": "分享@Hokai//2019再见@Createlite", "width": 1080, "height": 2160, "username": "Createlite", "p_link": "https://ws1.sinaimg.cn/large/006N1muNly1fypnfkb8z2j30u01o0nmk.jpg", "local_url": "https://img.dpic.dev/22ee4b8de21d538108379856b81048b6", "TID": "4ac1c07f-a9f7-11e8-a8ea-0202761b0892", "p_date": "2019-01-01", "theme_color": "#ffffff", "text_color": "#000000", "nativePath": "/201901/22ee4b8de21d538108379856b81048b6.jpg", "s1_url": "https://s1.images.dailypics.cn/201901/22ee4b8de21d538108379856b81048b6.jpg", "s2_url": "https://s2.images.dailypics.cn/201901/22ee4b8de21d538108379856b81048b6.jpg", "type": ".jpg", "aspect_ratio": "1:2", "info": {"image": {"size": 0, "format": "null"}, "exif": {}}, "size_b": 0, "size_kb": 0.0, "size_mb": 0.0, "size": "0.0KB", "p_content_html": "<p>分享@Hokai//2019再见@Createlite</p>", "if_today": false, "ago": 1177, "ago_zh": "1177天前"}, {"PID": "ccde8184-0785-11e9-8bad-0202761b0892", "p_title": "英梨梨", "p_content": "分享@Hokai//Createlite", "width": 1080, "height": 2160, "username": "Createlite", "p_link": "https://ws1.sinaimg.cn/large/006N1muNly1fyi6usq07rj30u01o0dj6.jpg", "local_url": "https://img.dpic.dev/797eb3c4bb0baebe6647868da29d4501", "TID": "4ac1c07f-a9f7-11e8-a8ea-0202761b0892", "p_date": "2018-12-25", "theme_color": "#30d0f2", "text_color": "#000000", "nativePath": "/201812/797eb3c4bb0baebe6647868da29d4501.jpg", "s1_url": "https://s1.images.dailypics.cn/201812/797eb3c4bb0baebe6647868da29d4501.jpg", "s2_url": "https://s2.images.dailypics.cn/201812/797eb3c4bb0baebe6647868da29d4501.jpg", "type": ".jpg", "aspect_ratio": "1:2", "info": {"image": {"size": 0, "format": "null"}, "exif": {}}, "size_b": 0, "size_kb": 0.0, "size_mb": 0.0, "size": "0.0KB", "p_content_html": "<p>分享@Hokai//Createlite</p>", "if_today": false, "ago": 1184, "ago_zh": "1184天前"}, {"PID": "798e19c3-fe1c-11e8-b735-0202761b0892", "p_title": "插图一张", "p_content": "分享：酷安@果冻山脉//@Createlite", "width": 1080, "height": 2160, "username": "Createlite", "p_link": "https://i.loli.net/2018/12/12/5c111ec187796.jpg", "local_url": "https://img.dpic.dev/6e1d99a5eac66b94a5b64fcff6441a53", "TID": "4ac1c07f-a9f7-11e8-a8ea-0202761b0892", "p_date": "2018-12-13", "theme_color": "#5c523b", "text_color": "#ffffff", "nativePath": "/201812/6e1d99a5eac66b94a5b64fcff6441a53.jpg", "s1_url": "https://s1.images.dailypics.cn/201812/6e1d99a5eac66b94a5b64fcff6441a53.jpg", "s2_url": "https://s2.images.dailypics.cn/201812/6e1d99a5eac66b94a5b64fcff6441a53.jpg", "type": ".jpg", "aspect_ratio": "1:2", "info": {"image": {"size": 0, "format": "null"}, "exif": {}}, "size_b": 0, "size_kb": 0.0, "size_mb": 0.0, "size": "0.0KB", "p_content_html": "<p>分享：酷安@果冻山脉//@Createlite</p>", "if_today": false, "ago": 1196, "ago_zh": "1196天前"}, {"PID": "5792d822-975a-11e9-af82-f23c914b97eb", "p_title": "视差", "p_content": "图源：酷安  \n//在手机里蔓延出的无限世界...", "width": 1080, "height": 2160, "username": "Createlite", "p_link": "https://img.dpic.dev/9d663444d1750e91af858b16d30b31fd", "local_url": "https://img.dpic.dev/9d663444d1750e91af858b16d30b31fd", "TID": "5398f27b-a9f7-11e8-a8ea-0202761b0892", "p_date": "2019-06-26", "theme_color": "#232f2e", "text_color": "#ffffff", "nativePath": "/201906/9d663444d1750e91af858b16d30b31fd.jpg", "s1_url": "https://s1.images.dailypics.cn/201906/9d663444d1750e91af858b16d30b31fd.jpg", "s2_url": "https://s2.images.dailypics.cn/201906/9d663444d1750e91af858b16d30b31fd.jpg", "type": ".jpg", "aspect_ratio": "1:2", "info": {"image": {"size": 0, "format": "null"}, "exif": {}}, "size_b": 0, "size_kb": 0.0, "size_mb": 0.0, "size": "0.0KB", "p_content_html": "<p>图源：酷安  <br />\n//在手机里蔓延出的无限世界...</p>", "if_today": false, "ago": 1001, "ago_zh": "1001天前"}, {"PID": "bcf43b08-87ad-11e9-907b-f23c914b97eb", "p_title": "风车", "p_content": "图源：Coolapk  \n分享：毕加索的狗  \n//仰望蓝天...  \n闲暇的时候，总喜欢静静的仰望蓝天，看蓝天的高远与湛蓝宁静与深邃，或者看蓝天中那云卷云舒，飘逸、抒情。", "width": 1080, "height": 2160, "username": "Createlite", "p_link": "https://img.dpic.dev/1b7de0d7a8d54dbf85a65d1cbbbd3dbf", "local_url": "https://img.dpic.dev/1b7de0d7a8d54dbf85a65d1cbbbd3dbf", "TID": "5398f27b-a9f7-11e8-a8ea-0202761b0892", "p_date": "2019-06-06", "theme_color": "#117188", "text_color": "#ffffff", "nativePath": "/201906/1b7de0d7a8d54dbf85a65d1cbbbd3dbf.jpg", "s1_url": "https://s1.images.dailypics.cn/201906/1b7de0d7a8d54dbf85a65d1cbbbd3dbf.jpg", "s2_url": "https://s2.images.dailypics.cn/201906/1b7de0d7a8d54dbf85a65d1cbbbd3dbf.jpg", "type": ".jpg", "aspect_ratio": "1:2", "info": {"image": {"size": 0, "format": "null"}, "exif": {}}, "size_b": 0, "size_kb": 0.0, "size_mb": 0.0, "size": "0.0KB", "p_content_html": "<p>图源：Coolapk  <br />\n分享：毕加索的狗  <br />\n//仰望蓝天...  <br />\n闲暇的时候，总喜欢静静的仰望蓝天，看蓝天的高远与湛蓝宁静与深邃，或者看蓝天中那云卷云舒，飘逸、抒情。</p>", "if_today": false, "ago": 1021, "ago_zh": "1021天前"}, {"PID": "56714aff-78bf-11e9-9337-f23c914b97eb", "p_title": "MOMENT", "p_content": "摄影：时雨西江  \n//NOW,AT THE MOMENT,HERE WE GO!", "width": 2000, "height": 4000, "username": "Createlite", "p_link": "https://img.dpic.dev/dbffdb96c9637fbff43069e1692d11d6", "local_url": "https://img.dpic.dev/dbffdb96c9637fbff43069e1692d11d6", "TID": "5398f27b-a9f7-11e8-a8ea-0202761b0892", "p_date": "2019-05-18", "theme_color": "#9b8f88", "text_color": "#000000", "nativePath": "/201905/dbffdb96c9637fbff43069e1692d11d6.jpg", "s1_url": "https://s1.images.dailypics.cn/201905/dbffdb96c9637fbff43069e1692d11d6.jpg", "s2_url": "https://s2.images.dailypics.cn/201905/dbffdb96c9637fbff43069e1692d11d6.jpg", "type": ".jpg", "aspect_ratio": "1:2", "info": {"image": {"size": 0, "format": "null"}, "exif": {}}, "size_b": 0, "size_kb": 0.0, "size_mb": 0.0, "size": "0.0KB", "p_content_html": "<p>摄影：时雨西江  <br />\n//NOW,AT THE MOMENT,HERE WE GO!</p>", "if_today": false, "ago": 1040, "ago_zh": "1040天前"}, {"PID": "3bc0bb71-6c2c-11e9-a8ca-f23c914b97eb", "p_title": "伞", "p_content": "图源：Coolapk @毕加索的狗  \n//沈阳这两天也是，小雨、阵雨淅淅沥沥，下个不停", "width": 1080, "height": 2160, "username": "Createlite", "p_link": "https://img.dpic.dev/8948501d88526216f015957cbbd5773d", "local_url": "https://img.dpic.dev/8948501d88526216f015957cbbd5773d", "TID": "5398f27b-a9f7-11e8-a8ea-0202761b0892", "p_date": "2019-05-02", "theme_color": "#131c23", "text_color": "#ffffff", "nativePath": "/201905/8948501d88526216f015957cbbd5773d.jpg", "s1_url": "https://s1.images.dailypics.cn/201905/8948501d88526216f015957cbbd5773d.jpg", "s2_url": "https://s2.images.dailypics.cn/201905/8948501d88526216f015957cbbd5773d.jpg", "type": ".jpg", "aspect_ratio": "1:2", "info": {"image": {"size": 0, "format": "null"}, "exif": {}}, "size_b": 0, "size_kb": 0.0, "size_mb": 0.0, "size": "0.0KB", "p_content_html": "<p>图源：Coolapk @毕加索的狗  <br />\n//沈阳这两天也是，小雨、阵雨淅淅沥沥，下个不停</p>", "if_today": false, "ago": 1056, "ago_zh": "1056天前"}, {"PID": "6be646e6-641b-11e9-a958-f23c914b97eb", "p_title": "云", "p_content": "单纯的觉得好美  \n图源：Tujian 投稿  \n// 有的时候简单不也是一种美么", "width": 1080, "height": 2160, "username": "陌寒", "p_link": "https://ws1.sinaimg.cn/large/005SeDP8gy1g2aelm5wztj30u01o0ad4.jpg", "local_url": "https://img.dpic.dev/049f7da4bc510eb355ff1371a0770a11", "TID": "5398f27b-a9f7-11e8-a8ea-0202761b0892", "p_date": "2019-04-22", "theme_color": "#6569b3", "text_color": "#000000", "nativePath": "/201904/049f7da4bc510eb355ff1371a0770a11.jpg", "s1_url": "https://s1.images.dailypics.cn/201904/049f7da4bc510eb355ff1371a0770a11.jpg", "s2_url": "https://s2.images.dailypics.cn/201904/049f7da4bc510eb355ff1371a0770a11.jpg", "type": ".jpg", "aspect_ratio": "1:2", "info": {"image": {"size": 0, "format": "null"}, "exif": {}}, "size_b": 0, "size_kb": 0.0, "size_mb": 0.0, "size": "0.0KB", "p_content_html": "<p>单纯的觉得好美  <br />\n图源：Tujian 投稿  <br />\n// 有的时候简单不也是一种美么</p>", "if_today": false, "ago": 1066, "ago_zh": "1066天前"}, {"PID": "c0793a4b-44ba-11e9-8eca-f23c914b97eb", "p_title": "建筑", "p_content": "图源：Oneplus 内建壁纸  \n砖与瓦的交错，结构与智慧的结晶。  \n//补。", "width": 1080, "height": 2160, "username": "Galentwww", "p_link": "https://ws2.sinaimg.cn/large/005SeDP8gy1g108oosm58j30u01o04qp.jpg", "local_url": "https://img.dpic.dev/a0991b928d4ead4867410d0044565640", "TID": "5398f27b-a9f7-11e8-a8ea-0202761b0892", "p_date": "2019-03-12", "theme_color": "#87bac7", "text_color": "#000000", "nativePath": "/201903/a0991b928d4ead4867410d0044565640.jpg", "s1_url": "https://s1.images.dailypics.cn/201903/a0991b928d4ead4867410d0044565640.jpg", "s2_url": "https://s2.images.dailypics.cn/201903/a0991b928d4ead4867410d0044565640.jpg", "type": ".jpg", "aspect_ratio": "1:2", "info": {"image": {"size": 0, "format": "null"}, "exif": {}}, "size_b": 0, "size_kb": 0.0, "size_mb": 0.0, "size": "0.0KB", "p_content_html": "<p>图源：Oneplus 内建壁纸  <br />\n砖与瓦的交错，结构与智慧的结晶。  <br />\n//补。</p>", "if_today": false, "ago": 1107, "ago_zh": "1107天前"}, {"PID": "0e89a20e-0e91-11e9-b158-0202761b0892", "p_title": "杂图", "p_content": "分享@Alone820//Createlite", "width": 1080, "height": 2160, "username": "Createlite", "p_link": "https://i.loli.net/2019/04/27/5cc332242db8e.png", "local_url": "https://img.dpic.dev/3083d4903088b7a99ba2b0b64410a665", "TID": "5398f27b-a9f7-11e8-a8ea-0202761b0892", "p_date": "2019-01-03", "theme_color": "#3d6890", "text_color": "#000000", "nativePath": "/201901/3083d4903088b7a99ba2b0b64410a665.jpg", "s1_url": "https://s1.images.dailypics.cn/201901/3083d4903088b7a99ba2b0b64410a665.jpg", "s2_url": "https://s2.images.dailypics.cn/201901/3083d4903088b7a99ba2b0b64410a665.jpg", "type": ".jpg", "aspect_ratio": "1:2", "info": {"image": {"size": 0, "format": "null"}, "exif": {}}, "size_b": 0, "size_kb": 0.0, "size_mb": 0.0, "size": "0.0KB", "p_content_html": "<p>分享@Alone820//Createlite</p>", "if_today": false, "ago": 1175, "ago_zh": "1175天前"}, {"PID": "1184c067-abe8-11e8-a8ea-0202761b0892", "p_title": "电线", "p_content": "摄于昆明  \n拍摄者：翩翩少年2947404946  \n#风景", "width": 2036, "height": 4072, "username": "Createlite", "p_link": "https://i.loli.net/2018/07/19/5b50a2efd509b.jpg", "local_url": "https://img.dpic.dev/0eecb5c00e53e575666200d807465180", "TID": "5398f27b-a9f7-11e8-a8ea-0202761b0892", "p_date": "2018-07-19", "theme_color": "#346798", "text_color": "#000000", "nativePath": "/201807/0eecb5c00e53e575666200d807465180.jpg", "s1_url": "https://s1.images.dailypics.cn/201807/0eecb5c00e53e575666200d807465180.jpg", "s2_url": "https://s2.images.dailypics.cn/201807/0eecb5c00e53e575666200d807465180.jpg", "type": ".jpg", "aspect_ratio": "1:2", "info": {"image": {"size": 0, "format": "null"}, "exif": {}}, "size_b": 0, "size_kb": 0.0, "size_mb": 0.0, "size": "0.0KB", "p_content_html": "<p>摄于昆明  <br />\n拍摄者：翩翩少年2947404946    </p>\n<h1>风景</h1>", "if_today": false, "ago": 1343, "ago_zh": "1343天前"}]