{"PID": "c977136e-ac7f-11e9-8550-f23c914b97eb", "p_title": "\u53ef\u7231\u7684\u5929\u4f9d", "p_content": "/\u5728\u6d41\u661f\u5212\u8fc7\u7684\u77ac\u95f4\uff0c\u770b\u5f97\u89c1\u4f60\u7684\u7f8e\u597d/", "width": 900, "height": 1600, "username": "\u5c0f\u5f6d\u53cb", "p_link": "https://img.dpic.dev/f40b7cf26c8128c41b094b6105af75e6", "local_url": "https://img.dpic.dev/f40b7cf26c8128c41b094b6105af75e6", "TID": "4ac1c07f-a9f7-11e8-a8ea-0202761b0892", "p_date": "2019-07-23", "theme_color": "#8298b8", "text_color": "#000000", "nativePath": "/201907/f40b7cf26c8128c41b094b6105af75e6.jpg", "s1_url": "https://s1.images.dailypics.cn/201907/f40b7cf26c8128c41b094b6105af75e6.jpg", "s2_url": "https://s2.images.dailypics.cn/201907/f40b7cf26c8128c41b094b6105af75e6.jpg", "type": ".jpg", "aspect_ratio": "9:16", "info": {"image": {"size": 0, "format": "null"}, "exif": {}}, "size_b": 0, "size_kb": 0.0, "size_mb": 0.0, "size": "0.0KB", "p_content_html": "<p>/\u5728\u6d41\u661f\u5212\u8fc7\u7684\u77ac\u95f4\uff0c\u770b\u5f97\u89c1\u4f60\u7684\u7f8e\u597d/</p>", "if_today": false, "ago": 1015, "ago_zh": "1015\u5929\u524d"}