[{"PID": "535fbb16-546e-11ea-89f4-0202761b0196", "p_title": "空 銀子", "p_content": "《龙王的工作！》是由白鸟士郎创作的一部轻小说，作品以日本的将棋为题材，标题中的“龙王”则是日本将棋的最高头衔之一。  \n//总能感觉这个番有点点奇怪的感觉，是我的错觉还是~~炼铜术士的胜利~~？  \n作品简介选自萌娘百科  \n> 图源：[Pixiv@太もも](https://www.pixiv.net/artworks/67943903)", "width": 2894, "height": 4093, "username": "Night", "p_link": "https://img.dpic.dev/b35f2cb01b8d21c0040f272fa0ebcfb6", "local_url": "https://img.dpic.dev/b35f2cb01b8d21c0040f272fa0ebcfb6", "TID": "4ac1c07f-a9f7-11e8-a8ea-0202761b0892", "p_date": "2020-02-22", "theme_color": "#f6f6f5", "text_color": "#000000", "nativePath": "/202002/b35f2cb01b8d21c0040f272fa0ebcfb6.png", "s1_url": "https://s1.images.dailypics.cn/202002/b35f2cb01b8d21c0040f272fa0ebcfb6.png", "s2_url": "https://s2.images.dailypics.cn/202002/b35f2cb01b8d21c0040f272fa0ebcfb6.png", "type": ".png", "aspect_ratio": "9:12.7", "info": {"image": {"size": 0, "format": "null"}, "exif": {}}, "size_b": 0, "size_kb": 0.0, "size_mb": 0.0, "size": "0.0KB", "p_content_html": "<p>《龙王的工作！》是由白鸟士郎创作的一部轻小说，作品以日本的将棋为题材，标题中的“龙王”则是日本将棋的最高头衔之一。  <br />\n//总能感觉这个番有点点奇怪的感觉，是我的错觉还是<del>炼铜术士的胜利</del>？  <br />\n作品简介选自萌娘百科    </p>\n<blockquote>\n<p>图源：<a href=\"https://www.pixiv.net/artworks/67943903\">Pixiv@太もも</a></p>\n</blockquote>", "if_today": false, "ago": 898, "ago_zh": "898天前"}, {"PID": "d0f7c993-546c-11ea-89f4-0202761b0196", "p_title": "航空时钟 GMT 4200", "p_content": "空客 A320 是 1982 年开始设计的，当年的电子集成度不高，如果是现在的新飞机一般就不会有这种仪表了。  \n  \n// 好在这个东西不会人机对抗（手动滑稽）  \n~~本图由波音公司倾情赞助~~  \n  \n图源：[知乎@Karminski - 牙医](https://zhuanlan.zhihu.com/p/108039875)", "width": 6000, "height": 4000, "username": "神楽坂花火", "p_link": "https://img.dpic.dev/1e347de3262a91d4151645ac7745e271", "local_url": "https://img.dpic.dev/1e347de3262a91d4151645ac7745e271", "TID": "e5771003-b4ed-11e8-a8ea-0202761b0892", "p_date": "2020-02-22", "theme_color": "#4f453f", "text_color": "#ffffff", "nativePath": "/202002/1e347de3262a91d4151645ac7745e271.jpg", "s1_url": "https://s1.images.dailypics.cn/202002/1e347de3262a91d4151645ac7745e271.jpg", "s2_url": "https://s2.images.dailypics.cn/202002/1e347de3262a91d4151645ac7745e271.jpg", "type": ".jpg", "aspect_ratio": "3:2", "info": {"image": {"size": 0, "format": "null"}, "exif": {}}, "size_b": 0, "size_kb": 0.0, "size_mb": 0.0, "size": "0.0KB", "p_content_html": "<p>空客 A320 是 1982 年开始设计的，当年的电子集成度不高，如果是现在的新飞机一般就不会有这种仪表了。    </p>\n<p>// 好在这个东西不会人机对抗（手动滑稽）  <br />\n<del>本图由波音公司倾情赞助</del>    </p>\n<p>图源：<a href=\"https://zhuanlan.zhihu.com/p/108039875\">知乎@Karminski - 牙医</a></p>", "if_today": false, "ago": 898, "ago_zh": "898天前"}]