[{"PID": "fc28f7b6-562b-11e9-a958-f23c914b97eb", "p_title": "清姬", "p_content": "图源：Tujian 投稿  \n//这次是 @RainGo 的解释：（法兰西万岁是fgo召唤出法国皇后时的召唤语音，其实只是fgo玩家玩梗）  \n图好看就完事儿了", "width": 1358, "height": 1920, "username": "RinGo", "p_link": "https://ws1.sinaimg.cn/large/005SeDP8gy1g1pc4r6ywjj311q1hcwne.jpg", "local_url": "https://img.dpic.dev/133137cc560ea54c49cb40a8fb7efac7", "TID": "4ac1c07f-a9f7-11e8-a8ea-0202761b0892", "p_date": "2019-04-04", "theme_color": "#919c89", "text_color": "#000000", "nativePath": "/201904/133137cc560ea54c49cb40a8fb7efac7.jpg", "s1_url": "https://s1.images.dailypics.cn/201904/133137cc560ea54c49cb40a8fb7efac7.jpg", "s2_url": "https://s2.images.dailypics.cn/201904/133137cc560ea54c49cb40a8fb7efac7.jpg", "type": ".jpg", "aspect_ratio": "9:12.7", "info": {"image": {"size": 0, "format": "null"}, "exif": {}}, "size_b": 0, "size_kb": 0.0, "size_mb": 0.0, "size": "0.0KB", "p_content_html": "<p>图源：Tujian 投稿  <br />\n//这次是 @RainGo 的解释：（法兰西万岁是fgo召唤出法国皇后时的召唤语音，其实只是fgo玩家玩梗）  <br />\n图好看就完事儿了</p>", "if_today": false, "ago": 914, "ago_zh": "914天前"}, {"PID": "3f435dcb-562c-11e9-a958-f23c914b97eb", "p_title": "轨道", "p_content": "图源：Unsplash  \n//红色与蓝色，在轨道中的交织。", "width": 3024, "height": 4032, "username": "Createlite", "p_link": "https://i.loli.net/2019/04/27/5cc333d68ebd1.png", "local_url": "https://img.dpic.dev/18adc81cb32325c34adc435b8bed8a0e", "TID": "5398f27b-a9f7-11e8-a8ea-0202761b0892", "p_date": "2019-04-04", "theme_color": "#011621", "text_color": "#ffffff", "nativePath": "/201904/18adc81cb32325c34adc435b8bed8a0e.jpg", "s1_url": "https://s1.images.dailypics.cn/201904/18adc81cb32325c34adc435b8bed8a0e.jpg", "s2_url": "https://s2.images.dailypics.cn/201904/18adc81cb32325c34adc435b8bed8a0e.jpg", "type": ".jpg", "aspect_ratio": "3:4", "info": {"image": {"size": 0, "format": "null"}, "exif": {}}, "size_b": 0, "size_kb": 0.0, "size_mb": 0.0, "size": "0.0KB", "p_content_html": "<p>图源：Unsplash  <br />\n//红色与蓝色，在轨道中的交织。</p>", "if_today": false, "ago": 914, "ago_zh": "914天前"}, {"PID": "145c87b0-57b9-11e9-a958-f23c914b97eb", "p_title": "白上吹雪", "p_content": "图源：Tujian投稿  \n//awsl", "width": 1100, "height": 779, "username": "Lie_", "p_link": "https://i.loli.net/2019/04/27/5cc3324b62682.png", "local_url": "https://img.dpic.dev/d0f6a0c41b832a85929df8ffa7cf4474", "TID": "e5771003-b4ed-11e8-a8ea-0202761b0892", "p_date": "2019-04-04", "theme_color": "#6e706f", "text_color": "#000000", "nativePath": "/201904/d0f6a0c41b832a85929df8ffa7cf4474.jpg", "s1_url": "https://s1.images.dailypics.cn/201904/d0f6a0c41b832a85929df8ffa7cf4474.jpg", "s2_url": "https://s2.images.dailypics.cn/201904/d0f6a0c41b832a85929df8ffa7cf4474.jpg", "type": ".jpg", "aspect_ratio": "16:11.3", "info": {"image": {"size": 0, "format": "null"}, "exif": {}}, "size_b": 0, "size_kb": 0.0, "size_mb": 0.0, "size": "0.0KB", "p_content_html": "<p>图源：Tujian投稿  <br />\n//awsl</p>", "if_today": false, "ago": 914, "ago_zh": "914天前"}, {"PID": "ca069de5-5775-11e9-a958-f23c914b97eb", "p_title": "天津之眼", "p_content": "摄影地：天津  \n设备：Oneplus 5  \n摄影：@CrazyDaemon", "width": 3838, "height": 2159, "username": "Createlite", "p_link": "https://ws4.sinaimg.cn/large/005SeDP8gy1g1rsptqzpgj32ym1nz7wh.jpg", "local_url": "https://img.dpic.dev/844eed065cd8db3812ff5d16641e3cd9", "TID": "e5771003-b4ed-11e8-a8ea-0202761b0892", "p_date": "2019-04-04", "theme_color": "#255ea4", "text_color": "#ffffff", "nativePath": "/201904/844eed065cd8db3812ff5d16641e3cd9.jpg", "s1_url": "https://s1.images.dailypics.cn/201904/844eed065cd8db3812ff5d16641e3cd9.jpg", "s2_url": "https://s2.images.dailypics.cn/201904/844eed065cd8db3812ff5d16641e3cd9.jpg", "type": ".jpg", "aspect_ratio": "16:9", "info": {"image": {"size": 0, "format": "null"}, "exif": {}}, "size_b": 0, "size_kb": 0.0, "size_mb": 0.0, "size": "0.0KB", "p_content_html": "<p>摄影地：天津  <br />\n设备：Oneplus 5  <br />\n摄影：@CrazyDaemon</p>", "if_today": false, "ago": 914, "ago_zh": "914天前"}]