{"PID": "f84dd3e7-5076-11ea-89f4-0202761b0196", "p_title": "\u660e\u65e5\u65b9\u821f", "p_content": "\u535a\u58eb\uff0c\u6211\u4eec\u4e00\u8d77\u52a0\u6cb9\u5427  \n  \n > \u56fe\u6e90:[Yande.re](https://yande.re/post/show/413674)", "width": 1693, "height": 1058, "username": "Galentwww", "p_link": "https://img.dpic.dev/2ce8e424a27ecddab43eb8f0148e3b87", "local_url": "https://img.dpic.dev/2ce8e424a27ecddab43eb8f0148e3b87", "TID": "e5771003-b4ed-11e8-a8ea-0202761b0892", "p_date": "2020-02-17", "theme_color": "#21161a", "text_color": "#ffffff", "nativePath": "/202002/2ce8e424a27ecddab43eb8f0148e3b87.jpg", "s1_url": "https://s1.images.dailypics.cn/202002/2ce8e424a27ecddab43eb8f0148e3b87.jpg", "s2_url": "https://s2.images.dailypics.cn/202002/2ce8e424a27ecddab43eb8f0148e3b87.jpg", "type": ".jpg", "aspect_ratio": "16:10", "info": {"image": {"size": 0, "format": "null"}, "exif": {}}, "size_b": 0, "size_kb": 0.0, "size_mb": 0.0, "size": "0.0KB", "p_content_html": "<p>\u535a\u58eb\uff0c\u6211\u4eec\u4e00\u8d77\u52a0\u6cb9\u5427    </p>\n<blockquote>\n<p>\u56fe\u6e90:<a href=\"https://yande.re/post/show/413674\">Yande.re</a></p>\n</blockquote>", "if_today": false, "ago": 600, "ago_zh": "600\u5929\u524d"}